jawsume/__init__.py
jawsume-0.1.0.dist-info/LICENSE
jawsume-0.1.0.dist-info/METADATA
jawsume-0.1.0.dist-info/WHEEL
jawsume-0.1.0.dist-info/top_level.txt
jawsume-0.1.0.dist-info/RECORD
