Metadata-Version: 2.1
Name: jawsume
Version: 0.1.0
Summary: Use AWSume in Jupyter
Author-email: Franz Diebold <franz@diebold.io>
License: MIT License        
Project-URL: Homepage, https://github.com/FranzDiebold/jawsume
Project-URL: Repository, https://github.com/FranzDiebold/jawsume
Keywords: jupyter,awsume,aws
Classifier: License :: OSI Approved :: MIT License
Classifier: Programming Language :: Python
Classifier: Programming Language :: Python :: 3
Requires-Python: >=3.6
License-File: LICENSE
Requires-Dist: awsume
Provides-Extra: build
Requires-Dist: build ; extra == 'build'
